dizzydecor/__init__.py
dizzydecor-0.0.4.dist-info/LICENSE
dizzydecor-0.0.4.dist-info/METADATA
dizzydecor-0.0.4.dist-info/WHEEL
dizzydecor-0.0.4.dist-info/top_level.txt
dizzydecor-0.0.4.dist-info/RECORD
