Metadata-Version: 2.1
Name: dizzydecor
Version: 0.0.4
Summary: Web service decorators for tornado
Home-page: https://github.com/TylerZeroMaster/dizzydecor
Author: Tyler Nullmeier
Author-email: Tylerzeromaster@gmail.com
License: MIT
Keywords: tornado webservice web service oriented SOA decorator
Platform: UNKNOWN
Classifier: Development Status :: 3 - Alpha
Classifier: Topic :: Utilities
Classifier: Programming Language :: Python :: 3 :: Only
Classifier: License :: OSI Approved :: MIT License
Requires-Python: >=3
Requires-Dist: tornado
